{"type":"Feature","id":2986,"geometry":{"type":"Point","coordinates":[47.35199926379413,8.346657179640983]},"properties":{"land":"\"velo\",\"mountainbike\"","category":"all","language":"en","title":"Willi's Zweiradhaus GmbH","abstract":null,"name":"Willi's Zweiradhaus GmbH","street":"Zürcherstrasse 19","zip":"5620","place":"Bremgarten AG","tel":"+41 56 633 30 10","email":null,"url1_text":null,"url1_link":"https://www.zweiradhaus.ch","organisation":"2rad / 2routes / 2ruote","foto":null,"foto_abstract":null,"x_coordinate":668607.2739097949,"y_coordinate":244969.7686256491,"change_date":null,"id":210,"type":"Service"}}