{"type":"Feature","id":3046,"geometry":{"type":"Point","coordinates":[46.863132927473444,8.65370180971102]},"properties":{"land":"\"velo\",\"mountainbike\"","category":"all","language":"en","title":"Megnet Alfred","abstract":null,"name":"Megnet Alfred","street":"Schulhausstrasse 14","zip":"6467","place":"Schattdorf","tel":"+41 41 870 02 32","email":null,"url1_text":null,"url1_link":null,"organisation":"2rad / 2routes / 2ruote","foto":null,"x_coordinate":692646.6534860804,"y_coordinate":190940.20296507244,"change_date":null,"id":281,"type":"Service"}}