{"type":"Feature","id":183,"geometry":{"type":"Point","coordinates":[46.20710962215914,6.859817151469275]},"properties":{"land":null,"category":"all","language":"en","title":"La Ferme à Gaby","abstract":"La Ferme à Gaby, a typical chalet of the Illiez Valley, was built in 1998 in the purest respect of the traditional methods. There, you will discover local products and cheese fabrication.","description":"This farm has different rooms to explain each activity. Upstairs, you will find the barn where hay is stored. There is also a museum in which you will be able to discover the utensils used in the mountains in the past.\n\nDownstairs, discover the cheese dairy. Cheese is made from raw milk on a fire. The impressive cauldron of 1'400 liters sits on a wooden support.\n\nNext to the cauldron, observe the caves behind a glass display. Finally, on the ground floor, visit the small shop selling local products. Possibility of booking meals for groups of 10 to 20 people as well.","highlights":null,"foto":"https://images0.schweizmobil.ch/image/11336_Ferme_a_Gaby_1a.jpg","photo_gallery":["https://images0.schweizmobil.ch/image/11336_Ferme_a_Gaby_1a.jpg","https://images0.schweizmobil.ch/image/11336_Ferme_a_Gaby_2b.jpg"],"photo_gallery_big":["",""],"photo_gallery_copyright":["",""],"photo_gallery_author":["",""],"name":"La Ferme à Gaby","name_2":null,"street":"Blaise Perrin","zip":"1873","place":"Champoussin","tel":"+41 (0)24 477 30 88","fax":null,"email":"contact@lafermeagaby.ch","url1_link":"https://www.lafermeagaby.ch","x_coordinate":555327.7065863652,"y_coordinate":117460.49724558083,"change_date":null,"id":183,"r_key":183,"type":"Sight","url_sightseeing":"https://www.lafermeagaby.ch","touristic_region":11}}