{"id":2147000265,"properties":{"title":"Täschhütte SAC","abstract":null,"description":"An alpine cabin in Mattertal surrounded by the well-known four-thousanders of the Mischabel range. The popular mountain hostel above Täschalp is primarily the starting point of various high alpine tours. The view from the newly constructed building goes directly to Weisshorn and Zinalrothorn on the other side of the valley. Looking southwards across Pfulwepass one can see Dufourspitze. In spring there are attractive, but challenging ski mountaineering tours.","r_number":2147000265,"city":"Valais","place":"Valais","tel":"+41 27 967 39 13","email":"info@taeschhuette.ch","url1_link":"https://www.taeschhuette.ch","photo_gallery_big":["https://static.suissealpine.sac-cas.ch/1530026925_416143114.jpg","https://static.suissealpine.sac-cas.ch/1545129900_1940550421.jpg","https://static.suissealpine.sac-cas.ch/1530025978_450484393.jpg","https://static.suissealpine.sac-cas.ch/1530025977_883029255.jpg","https://static.suissealpine.sac-cas.ch/1530025977_1250735265.jpg","https://static.suissealpine.sac-cas.ch/1530025977_397228766.jpg","https://static.suissealpine.sac-cas.ch/1530027591_1607056416.jpg","https://static.suissealpine.sac-cas.ch/1530025977_1694100332.jpg","https://static.suissealpine.sac-cas.ch/1530025977_1748874560.jpg","https://static.suissealpine.sac-cas.ch/1530025983_741967454.jpg","https://static.suissealpine.sac-cas.ch/1530025983_2022181650.jpg","https://static.suissealpine.sac-cas.ch/1530025984_444477407.jpg","https://static.suissealpine.sac-cas.ch/1530025983_830774007.jpg"]},"geometry":{"coordinates":[46.05165969492871,7.830110567192623]}}