{"id":2147000015,"properties":{"title":"Cabane d'Antème","description":"Overlooking the Val d'Illiez, the hut is situated in a picturesque spot just by a couple of small mountain lakes. It sits at the base of the steep walls leading up to the peak of Haute Cime, with a view over the Portes de Soleil area. Open from mid-June to the beginning of October, according to weather conditions.","r_number":2147000015,"city":"Valais","place":"Valais","tel":"+41 79 473 71 40","email":null,"url1_link":"http://antheme.ch/","photo_gallery_big":["https://static.suissealpine.sac-cas.ch/1593769631_390933330.jpg"]},"geometry":{"coordinates":[46.16576766585473,6.904185737708291]}}