{
    "type": "Feature",
    "id": 36862,
    "geometry": {
        "type": "Point",
        "coordinates": [
            46.77718066749721,
            8.956068875538044
        ]
    },
    "properties": {
        "id": 27754,
        "land": "\"wander\",\"velo\",\"mountainbike\",\"skating\",\"kanu\",\"winterhiking\",\"snowshoe\",\"crosscountry\",\"sledging\"",
        "type": "Uebernachte",
        "types": [
            "groupaccom",
            "mountainhut"
        ],
        "category": "all",
        "language": "en",
        "name": "Camona da Punteglias CAS",
        "stars_hotellerie": null,
        "stars_parahotellerie": null,
        "q_label": null,
        "hotelgroup": "Schweizer Alpen-Club SAC",
        "street": null,
        "zip": "7166",
        "place": "Trun",
        "tel": "+41 (0)81 943 19 36",
        "beds": 35,
        "campingplaces": null,
        "pricefrom": 60,
        "priceto": 70,
        "price_week": null,
        "email": "info@punteglias.ch",
        "url1_text": "www.punteglias.ch",
        "url1_link": "https://www.punteglias.ch",
        "url2_text": null,
        "url2_link": null,
        "foto": "https://images.schweizmobil.ch/image/Camona_da_Punteglias_CAS.jpg",
        "foto_abstract": null,
        "x_coordinate": 715883.8445932859,
        "y_coordinate": 181788.5221820089,
        "change_date": null
    }
}