{
    "type": "Feature",
    "id": 37651,
    "geometry": {
        "type": "Point",
        "coordinates": [
            46.846127261331,
            8.462790149497886
        ]
    },
    "properties": {
        "id": 27767,
        "land": "\"wander\",\"velo\",\"mountainbike\",\"skating\",\"kanu\",\"winterhiking\",\"snowshoe\",\"crosscountry\",\"sledging\"",
        "type": "Uebernachte",
        "types": [
            "groupaccom",
            "mountainhut"
        ],
        "category": "all",
        "language": "en",
        "name": "Rugghubelhütte SAC",
        "stars_hotellerie": null,
        "stars_parahotellerie": null,
        "q_label": null,
        "hotelgroup": "Schweizer Alpen-Club SAC",
        "street": null,
        "zip": "6390",
        "place": "Engelberg",
        "tel": "+41 (0)41 637 20 64",
        "beds": 95,
        "campingplaces": null,
        "pricefrom": 65,
        "priceto": 85,
        "price_week": null,
        "email": "info@rugghubel.ch",
        "url1_text": "www.rugghubel.ch",
        "url1_link": "https://www.rugghubel.ch",
        "url2_text": "Online booking",
        "url2_link": "http://www.alpenonline.ch/reservation/calendar?hut_id=41&lang=de",
        "foto": "https://images.schweizmobil.ch/image-big/SAC_Rugghubelhuette_2022_g.jpg",
        "foto_abstract": null,
        "x_coordinate": 678115.0273523796,
        "y_coordinate": 188842.7906095776,
        "change_date": null
    }
}