{"type":"Feature","id":30831,"geometry":{"type":"Point","coordinates":[46.56274649733346,7.97439948754548]},"properties":{"id":30976,"land":"\"wander\",\"velo\",\"mountainbike\",\"skating\",\"kanu\",\"winterhiking\",\"snowshoe\",\"crosscountry\",\"sledging\"","type":"Uebernachte","types":["mountainhut"],"category":"all","language":"en","name":"Guggihütte SAC (teilweise bewartet)","stars_hotellerie":null,"stars_parahotellerie":null,"q_label":null,"hotelgroup":"Schweizer Alpen-Club SAC","street":null,"zip":"3822","place":"Lauterbrunnen","tel":"+41 (0)33 855 31 57","beds":25,"campingplaces":null,"pricefrom":40.0,"priceto":60.0,"price_week":null,"email":"guggihuette@sac-interlaken.ch","url1_text":"www.sac-interlaken.ch","url1_link":"https://www.sac-interlaken.ch","url2_text":null,"url2_link":null,"foto":"https://images0.schweizmobil.ch/image-small/Lauterbrunnen_SAC_Guggihuette.jpg","x_coordinate":641080.0006093543,"y_coordinate":156970.00111661333,"change_date":null}}