{"type":"Feature","id":36635,"geometry":{"type":"Point","coordinates":[47.37375313263451,8.846943095649909]},"properties":{"id":33512,"land":"\"wander\",\"velo\",\"mountainbike\",\"skating\",\"kanu\",\"winterhiking\",\"snowshoe\",\"crosscountry\",\"sledging\"","type":"Uebernachte","types":["farmaccom"],"category":"all","language":"en","name":"Alpaka Zürich Oberland","stars_hotellerie":null,"stars_parahotellerie":null,"q_label":null,"hotelgroup":null,"street":"Niderdürstelenstrasse 66","zip":"8494","place":"Bauma","tel":"+41 (0)79 868 84 94","beds":2,"campingplaces":null,"pricefrom":85,"priceto":100,"price_week":null,"email":"hof@alpaka-zuerich-oberland.ch","url1_text":"www.alpaka-zuerich-oberland.ch","url1_link":"https://www.alpaka-zuerich-oberland.ch","url2_text":null,"url2_link":null,"foto":"https://images.schweizmobil.ch/image-big/Bauma_Alpaka_g.jpg","foto_abstract":null,"x_coordinate":706360.3489242824,"y_coordinate":247945.4878860951,"change_date":null}}