{
    "type": "Feature",
    "id": 5249,
    "geometry": {
        "type": "Point",
        "coordinates": [
            [
                46.987169781903134,
                6.889767836220497
            ]
        ]
    },
    "properties": {
        "land": "\"velo\",\"mountainbike\"",
        "category": "all",
        "language": "en",
        "title": "La Bicycletterie Suisse Sàrl",
        "abstract": null,
        "name": "La Bicycletterie Suisse Sàrl",
        "street": "Rue de la Fontaine 5",
        "zip": "2034",
        "place": "Peseux",
        "tel": "+41 32 740 18 07",
        "email": null,
        "url1_text": null,
        "url1_link": "https://www.labicycletterie.ch",
        "organisation": "2rad / 2routes / 2ruote",
        "foto": null,
        "foto_abstract": null,
        "x_coordinate": 558245.0265986061,
        "y_coordinate": 204158.52179483537,
        "change_date": null,
        "id": 622,
        "type": "Service"
    }
}