{
    "type": "Feature",
    "id": 2868,
    "geometry": {
        "type": "Point",
        "coordinates": [
            [
                46.929345318585405,
                7.119624736244357
            ]
        ]
    },
    "properties": {
        "land": "\"velo\",\"mountainbike\"",
        "category": "all",
        "language": "en",
        "title": "Bike Corner Murten",
        "abstract": null,
        "name": "Bike Corner Murten",
        "street": "Bernstrasse 3",
        "zip": "3280",
        "place": "Murten",
        "tel": "+41 26 670 57 33",
        "email": null,
        "url1_text": null,
        "url1_link": "https://www.bikecornermurten.ch",
        "organisation": "2rad / 2routes / 2ruote",
        "foto": null,
        "foto_abstract": null,
        "x_coordinate": 575705.8370482768,
        "y_coordinate": 197633.67513168795,
        "change_date": null,
        "id": 78,
        "type": "Service"
    }
}